{
  "doc_id": "care10-p10-e1saferesidenthandlingprogrameducation_300a407857b0",
  "original_file": "data/raw/extendicare_kb/Care/Section 10- Safe Resident Handling/CARE10-P10-E1 Safe Resident Handling Program Education.pdf",
  "page_metadata": [
    {
      "page_number": 1,
      "char_count": 1910
    },
    {
      "page_number": 2,
      "char_count": 252
    },
    {
      "page_number": 3,
      "char_count": 314
    },
    {
      "page_number": 4,
      "char_count": 713
    },
    {
      "page_number": 5,
      "char_count": 896
    },
    {
      "page_number": 6,
      "char_count": 723
    },
    {
      "page_number": 7,
      "char_count": 481
    },
    {
      "page_number": 8,
      "char_count": 1764
    },
    {
      "page_number": 9,
      "char_count": 2458
    },
    {
      "page_number": 10,
      "char_count": 831
    },
    {
      "page_number": 11,
      "char_count": 702
    },
    {
      "page_number": 12,
      "char_count": 362
    },
    {
      "page_number": 13,
      "char_count": 181
    }
  ],
  "parse_job_id": null,
  "error": null
}